glyf/__init__.py
glyf/cmaps.py
glyf/plot.py
glyf/utils.py
glyf-0.0.1.dist-info/METADATA
glyf-0.0.1.dist-info/WHEEL
glyf-0.0.1.dist-info/licenses/LICENSE
glyf-0.0.1.dist-info/RECORD
