Metadata-Version: 2.1
Name: glyf
Version: 0.0.1
Summary: A library for easy plotting of multiple images and graphs
Project-URL: Homepage, https://github.com/cdtn/glyf
Project-URL: Bug Tracker, https://github.com/cdtn/glyf/issues
Author-email: Stepan Goryachev <glyfo@icloud.com>
License-File: LICENSE
Classifier: Development Status :: 1 - Planning
Classifier: License :: OSI Approved :: Apache Software License
Classifier: Operating System :: OS Independent
Classifier: Programming Language :: Python :: 3.8
Classifier: Topic :: Scientific/Engineering :: Visualization
Requires-Python: >=3.8
Requires-Dist: matplotlib
Requires-Dist: numpy
